speech2caret/__init__.py
speech2caret/config.py
speech2caret/main.py
speech2caret/recorder.py
speech2caret/speech_to_text.py
speech2caret/utils.py
speech2caret/virtual_keyboard.py
speech2caret-0.3.0.dist-info/WHEEL
speech2caret-0.3.0.dist-info/entry_points.txt
speech2caret-0.3.0.dist-info/METADATA
speech2caret-0.3.0.dist-info/RECORD
