Metadata-Version: 2.4
Name: speech2caret
Version: 0.3.0
Summary: Use your speech to write to the current caret position!
Keywords: speech recognition,speech to text,caret,artificial intelligence,cli
Author: asmith26
License-Expression: Apache-2.0
Classifier: Operating System :: POSIX :: Linux
Classifier: Programming Language :: Python :: 3.13
Classifier: Programming Language :: Python :: 3.14
Requires-Dist: evdev>=1.9.2
Requires-Dist: loguru>=0.7.3
Requires-Dist: sounddevice>=0.5.2
Requires-Dist: torch>=2.9.0
Requires-Dist: transformers>=4.53.0
Requires-Dist: jiwer>=4.0.0 ; extra == 'benchmark'
Requires-Dist: pandas>=2.3.0 ; extra == 'benchmark'
Requires-Python: >=3.13
Project-URL: Homepage, https://github.com/asmith26/speech2caret
Provides-Extra: benchmark
